chacha20poly1305/__init__.py
chacha20poly1305/chacha.py
chacha20poly1305/compat.py
chacha20poly1305/cryptomath.py
chacha20poly1305/poly1305.py
chacha20poly1305-0.0.2.dist-info/METADATA
chacha20poly1305-0.0.2.dist-info/RECORD
chacha20poly1305-0.0.2.dist-info/WHEEL
chacha20poly1305-0.0.2.dist-info/top_level.txt
