Metadata-Version: 2.1
Name: chacha20poly1305
Version: 0.0.2
Summary: Chacha20Poly1305
Home-page: https://github.com/ph4r05/py-chacha20poly1305
Author: Dusan Klinec
Author-email: dusan.klinec@gmail.com
License: LGPL
Platform: UNKNOWN
Classifier: Intended Audience :: Developers
Classifier: Programming Language :: Python
Classifier: Programming Language :: Python :: 2.7
Classifier: Programming Language :: Python :: 3.5
Classifier: Programming Language :: Python :: 3.6
Classifier: Topic :: Security
Provides-Extra: docs
Provides-Extra: dev
Provides-Extra: dev
Requires-Dist: pep8; extra == 'dev'
Requires-Dist: tox; extra == 'dev'
Requires-Dist: pypandoc; extra == 'dev'
Provides-Extra: docs
Requires-Dist: Sphinx (>=1.0); extra == 'docs'
Requires-Dist: sphinx-rtd-theme; extra == 'docs'
Requires-Dist: sphinxcontrib-programoutput; extra == 'docs'
